<?xml version="1.0" encoding="UTF-8"?>
<out>
	<class>
		<name>com.globalmaksimum.galata.jgroupsdeneme.AppTest</name>
		<method>
			<name>constructor</name>
			<invocation>
				<referenceType>junit.framework.TestCase</referenceType>
				<instructionName>constructor</instructionName>
				<line>20</line>
			</invocation>
		</method>
		<method>
			<name>suite</name>
			<invocation>
				<referenceType>junit.framework.TestSuite</referenceType>
				<instructionName>constructor</instructionName>
				<line>28</line>
			</invocation>
		</method>
		<method>
			<name>testApp</name>
			<invocation>
				<referenceType>com.globalmaksimum.galata.jgroupsdeneme.AppTest
				</referenceType>
				<instructionName>assertTrue</instructionName>
				<line>36</line>
			</invocation>
		</method>
	</class>
	<class>
		<name>com.globalmaksimum.galata.jgroupsdeneme.AppTest</name>
		<method>
			<name>constructor</name>
			<invocation>
				<referenceType>junit.framework.TestCase</referenceType>
				<instructionName>constructor</instructionName>
				<line>20</line>
			</invocation>
		</method>
		<method>
			<name>suite</name>
			<invocation>
				<referenceType>junit.framework.TestSuite</referenceType>
				<instructionName>constructor</instructionName>
				<line>28</line>
			</invocation>
		</method>
		<method>
			<name>testApp</name>
			<invocation>
				<referenceType>com.globalmaksimum.galata.jgroupsdeneme.AppTest
				</referenceType>
				<instructionName>assertTrue</instructionName>
				<line>36</line>
			</invocation>
		</method>
	</class>
	<class>
		<name>com.globalmaksimum.galata.jgroupsdeneme.App</name>
		<method>
			<name>constructor</name>
			<invocation>
				<referenceType>org.jgroups.ReceiverAdapter</referenceType>
				<instructionName>constructor</instructionName>
				<line>15</line>
			</invocation>
		</method>
		<method>
			<name>viewAccepted</name>
			<invocation>
				<referenceType>java.lang.StringBuilder</referenceType>
				<instructionName>toString</instructionName>
				<line>20</line>
			</invocation>
			<invocation>
				<referenceType>org.jgroups.Channel</referenceType>
				<instructionName>getClusterName</instructionName>
				<line>19</line>
			</invocation>
			<invocation>
				<referenceType>java.lang.StringBuilder</referenceType>
				<instructionName>append</instructionName>
				<line>19</line>
				<line>20</line>
				<line>20</line>
			</invocation>
			<invocation>
				<referenceType>java.io.PrintStream</referenceType>
				<instructionName>println</instructionName>
				<line>19</line>
			</invocation>
			<invocation>
				<referenceType>java.lang.StringBuilder</referenceType>
				<instructionName>constructor</instructionName>
				<line>19</line>
			</invocation>
		</method>
		<method>
			<name>suspect</name>
			<invocation>
				<referenceType>java.lang.StringBuilder</referenceType>
				<instructionName>toString</instructionName>
				<line>28</line>
			</invocation>
			<invocation>
				<referenceType>org.jgroups.Channel</referenceType>
				<instructionName>getClusterName</instructionName>
				<line>27</line>
			</invocation>
			<invocation>
				<referenceType>java.lang.StringBuilder</referenceType>
				<instructionName>append</instructionName>
				<line>27</line>
				<line>28</line>
				<line>28</line>
				<line>28</line>
			</invocation>
			<invocation>
				<referenceType>java.io.PrintStream</referenceType>
				<instructionName>println</instructionName>
				<line>27</line>
			</invocation>
			<invocation>
				<referenceType>java.lang.StringBuilder</referenceType>
				<instructionName>constructor</instructionName>
				<line>27</line>
			</invocation>
		</method>
		<method>
			<name>start</name>
			<invocation>
				<referenceType>org.jgroups.Channel</referenceType>
				<instructionName>connect</instructionName>
				<line>35</line>
			</invocation>
			<invocation>
				<referenceType>org.jgroups.JChannel</referenceType>
				<instructionName>constructor</instructionName>
				<line>33</line>
			</invocation>
			<invocation>
				<referenceType>org.jgroups.Channel</referenceType>
				<instructionName>setReceiver</instructionName>
				<line>34</line>
			</invocation>
		</method>
		<method>
			<name>main</name>
			<invocation>
				<referenceType>com.globalmaksimum.galata.jgroupsdeneme.App
				</referenceType>
				<instructionName>start</instructionName>
				<line>50</line>
			</invocation>
			<invocation>
				<referenceType>org.jgroups.util.Util</referenceType>
				<instructionName>sleep</instructionName>
				<line>57</line>
			</invocation>
			<invocation>
				<referenceType>java.lang.Exception</referenceType>
				<instructionName>printStackTrace</instructionName>
				<line>54</line>
			</invocation>
			<invocation>
				<referenceType>java.lang.System</referenceType>
				<instructionName>setProperty</instructionName>
				<line>49</line>
			</invocation>
			<invocation>
				<referenceType>com.globalmaksimum.galata.jgroupsdeneme.App
				</referenceType>
				<instructionName>constructor</instructionName>
				<line>47</line>
			</invocation>
			<invocation>
				<referenceType>java.lang.StringBuilder</referenceType>
				<instructionName>toString</instructionName>
				<line>48</line>
				<line>50</line>
			</invocation>
			<invocation>
				<referenceType>java.lang.String</referenceType>
				<instructionName>split</instructionName>
				<line>45</line>
			</invocation>
			<invocation>
				<referenceType>java.lang.StringBuilder</referenceType>
				<instructionName>append</instructionName>
				<line>48</line>
				<line>50</line>
			</invocation>
			<invocation>
				<referenceType>java.io.PrintStream</referenceType>
				<instructionName>println</instructionName>
				<line>48</line>
			</invocation>
			<invocation>
				<referenceType>java.lang.StringBuilder</referenceType>
				<instructionName>constructor</instructionName>
				<line>48</line>
				<line>50</line>
			</invocation>
		</method>
	</class>
</out>